shapelyM/__init__.py
shapelyM/helpers.py
shapelyM/linear_reference.py
shapelyM/measureLineString.py
shapelyM/measurePoint.py
shapelym-0.0.6.dev7.dist-info/WHEEL
shapelym-0.0.6.dev7.dist-info/METADATA
shapelym-0.0.6.dev7.dist-info/RECORD
