Metadata-Version: 2.1
Name: shapelyM
Version: 0.0.6.dev7
Summary: Linear referencing for shapley LineStrings
Author-email: Hazzed <hazzed@shapleyM.com>
Requires-Python: >=3.10
Classifier: Development Status :: 2 - Pre-Alpha
Classifier: Intended Audience :: Developers
Classifier: Intended Audience :: End Users/Desktop
Classifier: Programming Language :: Python :: 3.10
Classifier: Programming Language :: Python :: 3 :: Only
Requires-Dist: shapely
Requires-Dist: numpy
Requires-Dist: flit ; extra == "dev"
Requires-Dist: flake8 ; extra == "dev"
Requires-Dist: flake8-black ; extra == "dev"
Requires-Dist: flake8-docstrings ; extra == "dev"
Requires-Dist: black ; extra == "dev"
Requires-Dist: pytest ; extra == "dev"
Requires-Dist: isort ; extra == "dev"
Requires-Dist: mypy ; extra == "dev"
Requires-Dist: codecov ; extra == "dev"
Requires-Dist: pytest-cov ; extra == "dev"
Requires-Dist: pytest-mock ; extra == "dev"
Requires-Dist: bumpversion ; extra == "dev"
Requires-Dist: shapelyAcad ; extra == "dev"
Project-URL: homepage, https://github.com/Hazedd/shapelyM
Provides-Extra: dev
